Workbook

Sheet README
B2: SKYCONNECT AIRLINES - CAPITAL INVESTMENT FINANCIAL MODEL
B4: New Route & Fleet Expansion: Boston (BOS) to London (LHR), Boeing 787-9
B5: Prepared by: Financial Planning & Analysis (FP&A) Team
B6: Purpose: Investment appraisal for new long-haul route launch
B8: PROJECT OVERVIEW
B9: SkyConnect Airlines is evaluating a $47.0mm capital investment to launch a new long-haul route between Boston (BOS) and London (LHR) using a leased Boeing 787-9 aircraft. This workbook presents a complete investment appraisal using six standard corporate finance techniques, built on a single shared set of assumptions so the entire model updates instantly when inputs change.
B14: WORKBOOK STRUCTURE - HOW EACH MODEL WORKS
B15: 1. Assumptions | C15: Every hard-coded input lives here (bold blue font). Nothing is hardcoded anywhere else, every other tab pulls from this sheet via formula, so updating one number here recalculates the entire model.
B16: 2. Cash Flow Engine | C16: Builds the 10-year unlevered free cash flow projection (revenue, costs, D&A, tax, capex) that feeds the ROI, Payback, NPV and IRR tabs. This is the single source of truth for project cash flows.
B17: 3. ROI Model | C17: Return on Investment = Total Net Profit / Total Investment. Shows simple and annualized ROI, answering how much do we make back per dollar invested.
B18: 4. Payback Period | C18: Calculates simple and discounted payback, how many years until cumulative cash flow turns positive. Includes a break-even year interpolation formula.
B19: 5. NPV Model | C19: Discounts all future free cash flows to present value at the company WACC to test whether the route adds shareholder value (NPV > 0).
B20: 6. IRR Model | C20: Solves for the discount rate at which NPV = 0, and compares it to WACC and a sensitivity table across discount rates and revenue growth.
B21: 7. Customer LTV | C21: Models the lifetime value of a long-haul passenger, factoring in retention rate, contribution margin, and acquisition cost, to sanity-check the commercial assumptions behind the route.
B22: 8. Break-Even | C22: Solves for the passenger load / revenue level at which the route covers its fixed and variable costs, with a load-factor sensitivity table.
B24: MODEL CONVENTIONS (INDUSTRY STANDARD)
B25: Blue bold font | C25: Hardcoded input, the only cells you should ever type over
B26: Black font | C26: Formula / calculation, never hardcoded
B27: Green font | C27: Link pulling from another sheet in this workbook
B28: All models | C28: Zero hardcoded values inside formulas; all assumptions centralized on the Assumptions tab

Sheet Assumptions
B2: ASSUMPTIONS - SINGLE SOURCE OF TRUTH
B3: Change any yellow/blue cell below and the entire workbook recalculates.
B5: Assumption | C5: Value | D5: Unit | E5: Notes / Source
B6: A. INVESTMENT & PROJECT SCOPE
B7: Aircraft acquisition & cabin fit-out cost | C7: 42000000 | D7: USD | E7: Leased 787-9 induction + interior config, Source: Fleet Planning memo
B8: Route launch & working capital (crew, slots, marketing) | C8: 5000000 | D8: USD | E8: One-time launch cost, Source: Network Planning budget
B9: Project evaluation horizon | C9: 10 | D9: Years | E9: Years
B10: Salvage / residual value at end of horizon | C10: 5000000 | D10: USD | E10: Est. lease return / disposal value
B12: Total Initial Investment | C12: =C7+C8 -> 47000000
B14: B. REVENUE & OPERATING COST DRIVERS
B15: Year 1 route revenue | C15: 32000000 | D15: USD | E15: Load factor x seats x avg fare x frequency, Source: Network Planning
B16: Annual revenue growth rate | C16: 0.06 | D16: % | E16: Route maturity ramp-up, Source: Commercial forecast
B17: Operating costs (% of revenue) - fuel, crew, MRO, airport fees | C17: 0.66 | D17: % | E17: Source: Route P&L benchmark, comparable long-haul routes
B18: Depreciation life (straight-line) | C18: 10 | D18: Years | E18: Years, matches lease term
B19: Corporate tax rate | C19: 0.25 | D19: % | E19: Effective statutory rate
B20: Discount rate / WACC | C20: 0.09 | D20: % | E20: Source: Corporate Treasury
B22: C. PASSENGER & CUSTOMER LIFETIME VALUE (CLV) DRIVERS
B23: Average one-way fare per passenger | C23: 850 | E23: Blended cabin mix (Y/W/J), Source: Revenue Mgmt
B24: Average trips per customer per year | C24: 2.4 | E24: Loyalty program data, transatlantic segment
B25: Annual customer retention rate | C25: 0.72 | E25: Source: Loyalty program cohort analysis
B26: Contribution margin per ticket | C26: 0.34 | E26: After variable cost per passenger
B27: Customer acquisition cost (CAC) | C27: 140 | E27: Marketing & loyalty signup cost per customer
B29: D. BREAK-EVEN DRIVERS
B30: Annual fixed costs (crew base, slots, leasing, insurance) | C30: 21000000 | E30: Source: Route P&L fixed cost build-up
B31: Variable cost per passenger (fuel, catering, handling) | C31: 310 | E31: Source: Cost accounting, per-pax variable cost
B32: Average ticket price per passenger | C32: 850 | E32: Same as CLV fare assumption
B33: Aircraft seat capacity | C33: 296 | E33: 787-9 3-class configuration
B34: Planned annual frequencies (round trips) | C34: 365 | E34: Daily service

Sheet Cash Flow Engine
B2: CASH FLOW ENGINE - 10-YEAR UNLEVERED FREE CASH FLOW
B3: Feeds the ROI, Payback, NPV and IRR tabs. All figures in USD ($mm shown to nearest whole $).
B5: Year | C5: Year 0 | D5: Year 1 | E5: Year 2 | F5: Year 3 | G5: Year 4 | H5: Year 5 | I5: Year 6 | J5: Year 7 | K5: Year 8 | L5: Year 9 | M5: Year 10
B6: Route Revenue | C6: 0 | D6: =Assumptions!$C$15 -> 32000000 | E6: =D6*(1+Assumptions!$C$16) -> 33920000 | F6: =E6*(1+Assumptions!$C$16) -> 35955200 | G6: =F6*(1+Assumptions!$C$16) -> 38112512 | H6: =G6*(1+Assumptions!$C$16) -> 40399263 | I6: =H6*(1+Assumptions!$C$16) -> 42823218 | J6: =I6*(1+Assumptions!$C$16) -> 45392612 | K6: =J6*(1+Assumptions!$C$16) -> 48116168 | L6: =K6*(1+Assumptions!$C$16) -> 51003138 | M6: =L6*(1+Assumptions!$C$16) -> 54063327
B7: Operating Costs (fuel, crew, MRO, fees) | C7: 0 | D7: =-D6*Assumptions!$C$17 -> -21120000 | E7: =-E6*Assumptions!$C$17 -> -22387200 | F7: =-F6*Assumptions!$C$17 -> -23730432 | G7: =-G6*Assumptions!$C$17 -> -25154258 | H7: =-H6*Assumptions!$C$17 -> -26663513 | I7: =-I6*Assumptions!$C$17 -> -28263324 | J7: =-J6*Assumptions!$C$17 -> -29959124 | K7: =-K6*Assumptions!$C$17 -> -31756671 | ... M7: =-M6*Assumptions!$C$17 -> -35681796
B8: EBITDA | C8: =C6+C7 -> 0 | D8: =D6+D7 -> 10880000 | E8: =E6+E7 -> 11532800 | F8: =F6+F7 -> 12224768 | G8: =G6+G7 -> 12958254 | H8: =H6+H7 -> 13735749 | I8: =I6+I7 -> 14559894 | J8: =J6+J7 -> 15433488 | ... M8: =M6+M7 -> 18381531
B9: Depreciation (straight-line) | C9: 0 | D9: =-Assumptions!$C$7/Assumptions!$C$18 -> -4200000 | E9: =-Assumptions!$C$7/Assumptions!$C$18 -> -4200000 | F9: =-Assumptions!$C$7/Assumptions!$C$18 -> -4200000 | G9: =-Assumptions!$C$7/Assumptions!$C$18 -> -4200000 | H9: =-Assumptions!$C$7/Assumptions!$C$18 -> -4200000 | I9: =-Assumptions!$C$7/Assumptions!$C$18 -> -4200000 | J9: =-Assumptions!$C$7/Assumptions!$C$18 -> -4200000 | K9: =-Assumptions!$C$7/Assumptions!$C$18 -> -4200000 | ... M9: =-Assumptions!$C$7/Assumptions!$C$18 -> -4200000
B10: EBIT | C10: =C8+C9 -> 0 | D10: =D8+D9 -> 6680000 | E10: =E8+E9 -> 7332800 | F10: =F8+F9 -> 8024768 | G10: =G8+G9 -> 8758254.1 | H10: =H8+H9 -> 9535749.3 | I10: =I8+I9 -> 10359894 | J10: =J8+J9 -> 11233488 | ... M10: =M8+M9 -> 14181531
B11: Tax @ statutory rate | C11: =-MAX(C10,0)*Assumptions!$C$19 -> 0 | D11: =-MAX(D10,0)*Assumptions!$C$19 -> -1670000 | E11: =-MAX(E10,0)*Assumptions!$C$19 -> -1833200 | F11: =-MAX(F10,0)*Assumptions!$C$19 -> -2006192 | G11: =-MAX(G10,0)*Assumptions!$C$19 -> -2189563.5 | H11: =-MAX(H10,0)*Assumptions!$C$19 -> -2383937.3 | I11: =-MAX(I10,0)*Assumptions!$C$19 -> -2589973.6 | J11: =-MAX(J10,0)*Assumptions!$C$19 -> -2808372 | ... M11: =-MAX(M10,0)*Assumptions!$C$19 -> -3545382.8
B12: NOPAT (after-tax operating profit) | C12: =C10+C11 -> 0 | D12: =D10+D11 -> 5010000 | E12: =E10+E11 -> 5499600 | F12: =F10+F11 -> 6018576 | G12: =G10+G11 -> 6568690.6 | H12: =H10+H11 -> 7151812 | I12: =I10+I11 -> 7769920.7 | J12: =J10+J11 -> 8425116 | ... M12: =M10+M11 -> 10636148
B13: Add back: Depreciation | C13: =-C9 -> 0 | D13: =-D9 -> 4200000 | E13: =-E9 -> 4200000 | F13: =-F9 -> 4200000 | G13: =-G9 -> 4200000 | H13: =-H9 -> 4200000 | I13: =-I9 -> 4200000 | J13: =-J9 -> 4200000 | ... M13: =-M9 -> 4200000
B14: Capital Expenditure (aircraft + fit-out) | C14: =-Assumptions!$C$7 -> -42000000 | D14: 0 | E14: 0 | F14: 0 | G14: 0 | H14: 0 | I14: 0 | J14: 0 | K14: 0 | L14: 0 | M14: 0
B15: Working Capital / Route Launch Cost | C15: =-Assumptions!$C$8 -> -5000000 | D15: 0 | E15: 0 | F15: 0 | G15: 0 | H15: 0 | I15: 0 | J15: 0 | K15: 0 | L15: 0 | M15: 0
B16: After-tax Salvage Value (final year) | C16: 0 | D16: 0 | E16: 0 | F16: 0 | G16: 0 | H16: 0 | I16: 0 | J16: 0 | K16: 0 | L16: 0 | M16: =Assumptions!$C$10*(1-Assumptions!$C$19) -> 3750000
B17: Free Cash Flow (FCF) | C17: =C12+C13+C14+C15+C16 -> -47000000 | D17: =D12+D13+D14+D15+D16 -> 9210000 | E17: =E12+E13+E14+E15+E16 -> 9699600 | F17: =F12+F13+F14+F15+F16 -> 10218576 | G17: =G12+G13+G14+G15+G16 -> 10768691 | H17: =H12+H13+H14+H15+H16 -> 11351812 | I17: =I12+I13+I14+I15+I16 -> 11969921 | J17: =J12+J13+J14+J15+J16 -> 12625116 | ... M17: =M12+M13+M14+M15+M16 -> 18586148
B18: Cumulative Free Cash Flow | C18: =C17 -> -47000000 | D18: =C18+D17 -> -37790000 | E18: =D18+E17 -> -28090400 | F18: =E18+F17 -> -17871824 | G18: =F18+G17 -> -7103133.4 | H18: =G18+H17 -> 4248678.6 | I18: =H18+I17 -> 16218599 | J18: =I18+J17 -> 28843715 | K18: =J18+K17 -> 42163338 | ... M18: =L18+M17 -> 74805287
B20: EBITDA Margin % | C20: =IF(C6=0,"-",C8/C6) -> - | D20: =IF(D6=0,"-",D8/D6) -> 0.34 | E20: =IF(E6=0,"-",E8/E6) -> 0.34 | F20: =IF(F6=0,"-",F8/F6) -> 0.34 | G20: =IF(G6=0,"-",G8/G6) -> 0.34 | H20: =IF(H6=0,"-",H8/H6) -> 0.34 | I20: =IF(I6=0,"-",I8/I6) -> 0.34 | J20: =IF(J6=0,"-",J8/J6) -> 0.34 | ... M20: =IF(M6=0,"-",M8/M6) -> 0.34

Sheet ROI Model
B2: RETURN ON INVESTMENT (ROI) MODEL
B3: ROI = Total Net Profit generated / Total Capital Invested. Measures overall return efficiency.
B5: Metric | C5: Value
B6: Total Initial Investment | C6: =Assumptions!C12 -> 47000000
B7: Total Free Cash Flow generated (Years 1-10) | C7: =SUM('Cash Flow Engine'!D17:M17) -> 1.2180529e+08
B8: Total Net Profit (Total FCF less Initial Investment) | C8: =C7-C6 -> 74805287
B10: ROI RESULTS
B11: Simple ROI (%) | C11: =C8/C6 -> 1.5916018
B12: Project Life (Years) | C12: =Assumptions!C9 -> 10
B13: Annualized ROI (%) | C13: =C11/C12 -> 0.15916018
B14: ROI Multiple (x invested capital returned) | C14: =C7/C6 -> 2.5916018
B16: YEAR-BY-YEAR ROI BUILD-UP
B17: Year | C17: FCF | D17: Cumulative FCF | E17: Cumulative Net Profit | F17: Cumulative ROI %
B18: Year 1 | C18: ='Cash Flow Engine'!D17 -> 9210000 | D18: =SUM($C$18:C18) -> 9210000 | E18: =D18-$C$6 -> -37790000 | F18: =E18/$C$6 -> -0.80404255
B19: Year 2 | C19: ='Cash Flow Engine'!E17 -> 9699600 | D19: =SUM($C$18:C19) -> 18909600 | E19: =D19-$C$6 -> -28090400 | F19: =E19/$C$6 -> -0.59766809
B20: Year 3 | C20: ='Cash Flow Engine'!F17 -> 10218576 | D20: =SUM($C$18:C20) -> 29128176 | E20: =D20-$C$6 -> -17871824 | F20: =E20/$C$6 -> -0.38025157
B21: Year 4 | C21: ='Cash Flow Engine'!G17 -> 10768691 | D21: =SUM($C$18:C21) -> 39896867 | E21: =D21-$C$6 -> -7103133.4 | F21: =E21/$C$6 -> -0.1511305
B22: Year 5 | C22: ='Cash Flow Engine'!H17 -> 11351812 | D22: =SUM($C$18:C22) -> 51248679 | E22: =D22-$C$6 -> 4248678.6 | F22: =E22/$C$6 -> 0.090397416
B23: Year 6 | C23: ='Cash Flow Engine'!I17 -> 11969921 | D23: =SUM($C$18:C23) -> 63218599 | E23: =D23-$C$6 -> 16218599 | F23: =E23/$C$6 -> 0.34507658
B24: Year 7 | C24: ='Cash Flow Engine'!J17 -> 12625116 | D24: =SUM($C$18:C24) -> 75843715 | E24: =D24-$C$6 -> 28843715 | F24: =E24/$C$6 -> 0.61369607
B25: Year 8 | C25: ='Cash Flow Engine'!K17 -> 13319623 | D25: =SUM($C$18:C25) -> 89163338 | E25: =D25-$C$6 -> 42163338 | F25: =E25/$C$6 -> 0.8970923
B26: Year 9 | C26: ='Cash Flow Engine'!L17 -> 14055800 | D26: =SUM($C$18:C26) -> 1.0321914e+08 | E26: =D26-$C$6 -> 56219138 | F26: =E26/$C$6 -> 1.1961519
B27: Year 10 | C27: ='Cash Flow Engine'!M17 -> 18586148 | D27: =SUM($C$18:C27) -> 1.2180529e+08 | E27: =D27-$C$6 -> 74805287 | F27: =E27/$C$6 -> 1.5916018
B29: INTERPRETATION
B30: A Simple ROI above 0% means the route returns more cash than was invested over its 10-year life. Annualized ROI approximates the average yearly return and is best read alongside the IRR tab, which properly accounts for the time value of money.

Sheet Payback Period
B2: PAYBACK PERIOD MODEL (SIMPLE & DISCOUNTED)
B3: Years until cumulative cash flow turns positive - a liquidity / risk check that complements NPV and IRR.
B5: Year | C5: Year 0 | D5: Year 1 | E5: Year 2 | F5: Year 3 | G5: Year 4 | H5: Year 5 | I5: Year 6 | J5: Year 7 | K5: Year 8 | L5: Year 9 | M5: Year 10
B6: Free Cash Flow | C6: ='Cash Flow Engine'!C17 -> -47000000 | D6: ='Cash Flow Engine'!D17 -> 9210000 | E6: ='Cash Flow Engine'!E17 -> 9699600 | F6: ='Cash Flow Engine'!F17 -> 10218576 | G6: ='Cash Flow Engine'!G17 -> 10768691 | H6: ='Cash Flow Engine'!H17 -> 11351812 | I6: ='Cash Flow Engine'!I17 -> 11969921 | J6: ='Cash Flow Engine'!J17 -> 12625116 | ... M6: ='Cash Flow Engine'!M17 -> 18586148
B7: Cumulative FCF (Simple) | C7: =C6 -> -47000000 | D7: =C7+D6 -> -37790000 | E7: =D7+E6 -> -28090400 | F7: =E7+F6 -> -17871824 | G7: =F7+G6 -> -7103133.4 | H7: =G7+H6 -> 4248678.6 | I7: =H7+I6 -> 16218599 | J7: =I7+J6 -> 28843715 | K7: =J7+K6 -> 42163338 | ... M7: =L7+M6 -> 74805287
B9: Discount Rate (WACC) | C9: =Assumptions!C20 -> 0.09
B10: Discount Factor | C10: =1/(1+$C$9)^0 -> 1 | D10: =1/(1+$C$9)^1 -> 0.91743119 | E10: =1/(1+$C$9)^2 -> 0.84167999 | F10: =1/(1+$C$9)^3 -> 0.77218348 | G10: =1/(1+$C$9)^4 -> 0.70842521 | H10: =1/(1+$C$9)^5 -> 0.64993139 | I10: =1/(1+$C$9)^6 -> 0.59626733 | J10: =1/(1+$C$9)^7 -> 0.54703424 | K10: =1/(1+$C$9)^8 -> 0.50186628 | L10: =1/(1+$C$9)^9 -> 0.46042778 | M10: =1/(1+$C$9)^10 -> 0.42241081
B11: Discounted FCF | C11: =C6*C10 -> -47000000 | D11: =D6*D10 -> 8449541.3 | E11: =E6*E10 -> 8163959.3 | F11: =F6*F10 -> 7890615.6 | G11: =G6*G10 -> 7628811.9 | H11: =H6*H10 -> 7377898.9 | I11: =I6*I10 -> 7137272.6 | J11: =J6*J10 -> 6906370.8 | ... M11: =M6*M10 -> 7850989.9
B12: Cumulative Discounted FCF | C12: =C11 -> -47000000 | D12: =C12+D11 -> -38550459 | E12: =D12+E11 -> -30386499 | F12: =E12+F11 -> -22495884 | G12: =F12+G11 -> -14867072 | H12: =G12+H11 -> -7489173.1 | I12: =H12+I11 -> -351900.46 | J12: =I12+J11 -> 6554470.3 | K12: =J12+K11 -> 13239140 | ... M12: =L12+M11 -> 27561811
B14: PAYBACK RESULTS
B15: Full years before payback (simple) | C15: =IFERROR(MATCH(TRUE(),INDEX(C7:M7>0,0),0)-1,"Not achieved") -> 5
B16: Simple Payback Period (Years) | C16: =IF(ISNUMBER(C15),C15+(-INDEX(C7:M7,1,C15+1))/INDEX(C6:M6,1,C15+2),"Not achieved") -> 4.6450537
B17: Full years before payback (discounted) | C17: =IFERROR(MATCH(TRUE(),INDEX(C12:M12>0,0),0)-1,"Not achieved") -> 7
B18: Discounted Payback Period (Years) | C18: =IF(ISNUMBER(C17),C17+(-INDEX(C12:M12,1,C17+1))/INDEX(C11:M11,1,C17+2),"Not achieved") -> 6.0194773
B19: Project Life (Years) | C19: =Assumptions!C9 -> 10
B20: Payback vs Project Life | C20: =IF(C16<=C19,"PASS - Recovers capital within project life","FAIL - Does not recover within life") -> PASS - Recovers capital within project life

Sheet NPV Model
B2: NET PRESENT VALUE (NPV) MODEL
B3: NPV discounts every future free cash flow back to today at the WACC. NPV > 0 means the route creates shareholder value.
B5: Year | C5: Year 0 | D5: Year 1 | E5: Year 2 | F5: Year 3 | G5: Year 4 | H5: Year 5 | I5: Year 6 | J5: Year 7 | K5: Year 8 | L5: Year 9 | M5: Year 10
B6: Free Cash Flow | C6: ='Cash Flow Engine'!C17 -> -47000000 | D6: ='Cash Flow Engine'!D17 -> 9210000 | E6: ='Cash Flow Engine'!E17 -> 9699600 | F6: ='Cash Flow Engine'!F17 -> 10218576 | G6: ='Cash Flow Engine'!G17 -> 10768691 | H6: ='Cash Flow Engine'!H17 -> 11351812 | I6: ='Cash Flow Engine'!I17 -> 11969921 | J6: ='Cash Flow Engine'!J17 -> 12625116 | ... M6: ='Cash Flow Engine'!M17 -> 18586148
B7: Discount Factor @ WACC | C7: =1/(1+Assumptions!$C$20)^0 -> 1 | D7: =1/(1+Assumptions!$C$20)^1 -> 0.91743119 | E7: =1/(1+Assumptions!$C$20)^2 -> 0.84167999 | F7: =1/(1+Assumptions!$C$20)^3 -> 0.77218348 | G7: =1/(1+Assumptions!$C$20)^4 -> 0.70842521 | H7: =1/(1+Assumptions!$C$20)^5 -> 0.64993139 | I7: =1/(1+Assumptions!$C$20)^6 -> 0.59626733 | J7: =1/(1+Assumptions!$C$20)^7 -> 0.54703424 | K7: =1/(1+Assumptions!$C$20)^8 -> 0.50186628 | L7: =1/(1+Assumptions!$C$20)^9 -> 0.46042778 | M7: =1/(1+Assumptions!$C$20)^10 -> 0.42241081
B8: Present Value of FCF | C8: =C6*C7 -> -47000000 | D8: =D6*D7 -> 8449541.3 | E8: =E6*E7 -> 8163959.3 | F8: =F6*F7 -> 7890615.6 | G8: =G6*G7 -> 7628811.9 | H8: =H6*H7 -> 7377898.9 | I8: =I6*I7 -> 7137272.6 | J8: =J6*J7 -> 6906370.8 | ... M8: =M6*M7 -> 7850989.9
B10: NPV RESULTS
B11: Discount Rate (WACC) | C11: =Assumptions!C20 -> 0.09
B12: PV of Year 1-10 Free Cash Flows | C12: =SUM(D8:M8) -> 74561811
B13: Initial Investment (Year 0) | C13: =-C6 -> 47000000
B14: NET PRESENT VALUE (NPV) | C14: =C12-C13 -> 27561811
B15: Cross-check: NPV via NPV() function | C15: =NPV(Assumptions!$C$20,D6:M6)+C6 -> 27561811
B16: Profitability Index (PI = PV inflows / Investment) | C16: =C12/C13 -> 1.5864215
B17: Investment Decision | C17: =IF(C14>0,"ACCEPT - NPV is positive, adds shareholder value","REJECT - NPV is negative") -> ACCEPT - NPV is positive, adds shareholder value

Sheet IRR Model
B2: INTERNAL RATE OF RETURN (IRR) MODEL
B3: IRR is the discount rate at which NPV = 0. Compare IRR to WACC: IRR > WACC means the route beats the cost of capital.
B5: Year | C5: Year 0 | D5: Year 1 | E5: Year 2 | F5: Year 3 | G5: Year 4 | H5: Year 5 | I5: Year 6 | J5: Year 7 | K5: Year 8 | L5: Year 9 | M5: Year 10
B6: Free Cash Flow | C6: ='Cash Flow Engine'!C17 -> -47000000 | D6: ='Cash Flow Engine'!D17 -> 9210000 | E6: ='Cash Flow Engine'!E17 -> 9699600 | F6: ='Cash Flow Engine'!F17 -> 10218576 | G6: ='Cash Flow Engine'!G17 -> 10768691 | H6: ='Cash Flow Engine'!H17 -> 11351812 | I6: ='Cash Flow Engine'!I17 -> 11969921 | J6: ='Cash Flow Engine'!J17 -> 12625116 | ... M6: ='Cash Flow Engine'!M17 -> 18586148
B8: IRR RESULTS
B9: Internal Rate of Return (IRR) | C9: =IRR(C6:M6) -> 0.1968123
B10: WACC / Hurdle Rate | C10: =Assumptions!C20 -> 0.09
B11: IRR less WACC (spread) | C11: =C9-C10 -> 0.1068123
B12: Modified IRR (MIRR) - reinvest at WACC, finance at WACC | C12: =MIRR(C6:M6,C10,C10) -> 0.14148013
B13: Investment Decision | C13: =IF(C9>C10,"ACCEPT - IRR exceeds cost of capital","REJECT - IRR below cost of capital") -> ACCEPT - IRR exceeds cost of capital
B15: SENSITIVITY: NPV ($) BY DISCOUNT RATE vs REVENUE GROWTH RATE
B16: Rows = Discount Rate, Columns = Annual Revenue Growth Rate
B17: NPV ($) | C17: -0.02 | D17: 0 | E17: 0.02 | F17: 0.04 | G17: 0.06 | H17: 0.08 | I17: 0.1
B18: 0.05 | C18: =-Assumptions!$C$12+SUMPRODUCT(((Assumptions!$C$15*(1+C$17)^(ROW(INDIRECT("1:10"))-1)*(1-Assumptions!$C$17)-Assumptions!$C$7/Assumptions!$C$18)*(1-Assumptions!$C$19)+Assumptions!$C$7/Assumptions!$C$18)/(1+$B18)^ROW(INDIRECT("1:10")))+Assumptions!$C$10*(1-Assumptions!$C$19)/(1+$B18)^10 -> 21507818 | D18: =-Assumptions!$C$12+SUMPRODUCT(((Assumptions!$C$15*(1+D$17)^(ROW(INDIRECT("1:10"))-1)*(1-Assumptions!$C$17)-Assumptions!$C$7/Assumptions!$C$18)*(1-Assumptions!$C$19)+Assumptions!$C$7/Assumptions!$C$18)/(1+$B18)^ROW(INDIRECT("1:10")))+Assumptions!$C$10*(1-Assumptions!$C$19)/(1+$B18)^10 -> 26419353 | E18: =-Assumptions!$C$12+SUMPRODUCT(((Assumptions!$C$15*(1+E$17)^(ROW(INDIRECT("1:10"))-1)*(1-Assumptions!$C$17)-Assumptions!$C$7/Assumptions!$C$18)*(1-Assumptions!$C$19)+Assumptions!$C$7/Assumptions!$C$18)/(1+$B18)^ROW(INDIRECT("1:10")))+Assumptions!$C$10*(1-Assumptions!$C$19)/(1+$B18)^10 -> 31856939 | F18: =-Assumptions!$C$12+SUMPRODUCT(((Assumptions!$C$15*(1+F$17)^(ROW(INDIRECT("1:10"))-1)*(1-Assumptions!$C$17)-Assumptions!$C$7/Assumptions!$C$18)*(1-Assumptions!$C$19)+Assumptions!$C$7/Assumptions!$C$18)/(1+$B18)^ROW(INDIRECT("1:10")))+Assumptions!$C$10*(1-Assumptions!$C$19)/(1+$B18)^10 -> 37876863 | G18: =-Assumptions!$C$12+SUMPRODUCT(((Assumptions!$C$15*(1+G$17)^(ROW(INDIRECT("1:10"))-1)*(1-Assumptions!$C$17)-Assumptions!$C$7/Assumptions!$C$18)*(1-Assumptions!$C$19)+Assumptions!$C$7/Assumptions!$C$18)/(1+$B18)^ROW(INDIRECT("1:10")))+Assumptions!$C$10*(1-Assumptions!$C$19)/(1+$B18)^10 -> 44540907 | H18: =-Assumptions!$C$12+SUMPRODUCT(((Assumptions!$C$15*(1+H$17)^(ROW(INDIRECT("1:10"))-1)*(1-Assumptions!$C$17)-Assumptions!$C$7/Assumptions!$C$18)*(1-Assumptions!$C$19)+Assumptions!$C$7/Assumptions!$C$18)/(1+$B18)^ROW(INDIRECT("1:10")))+Assumptions!$C$10*(1-Assumptions!$C$19)/(1+$B18)^10 -> 51916802 | I18: =-Assumptions!$C$12+SUMPRODUCT(((Assumptions!$C$15*(1+I$17)^(ROW(INDIRECT("1:10"))-1)*(1-Assumptions!$C$17)-Assumptions!$C$7/Assumptions!$C$18)*(1-Assumptions!$C$19)+Assumptions!$C$7/Assumptions!$C$18)/(1+$B18)^ROW(INDIRECT("1:10")))+Assumptions!$C$10*(1-Assumptions!$C$19)/(1+$B18)^10 -> 60078721
B19: 0.07 | C19: =-Assumptions!$C$12+SUMPRODUCT(((Assumptions!$C$15*(1+C$17)^(ROW(INDIRECT("1:10"))-1)*(1-Assumptions!$C$17)-Assumptions!$C$7/Assumptions!$C$18)*(1-Assumptions!$C$19)+Assumptions!$C$7/Assumptions!$C$18)/(1+$B19)^ROW(INDIRECT("1:10")))+Assumptions!$C$10*(1-Assumptions!$C$19)/(1+$B19)^10 -> 15288577 | D19: =-Assumptions!$C$12+SUMPRODUCT(((Assumptions!$C$15*(1+D$17)^(ROW(INDIRECT("1:10"))-1)*(1-Assumptions!$C$17)-Assumptions!$C$7/Assumptions!$C$18)*(1-Assumptions!$C$19)+Assumptions!$C$7/Assumptions!$C$18)/(1+$B19)^ROW(INDIRECT("1:10")))+Assumptions!$C$10*(1-Assumptions!$C$19)/(1+$B19)^10 -> 19593496 | E19: =-Assumptions!$C$12+SUMPRODUCT(((Assumptions!$C$15*(1+E$17)^(ROW(INDIRECT("1:10"))-1)*(1-Assumptions!$C$17)-Assumptions!$C$7/Assumptions!$C$18)*(1-Assumptions!$C$19)+Assumptions!$C$7/Assumptions!$C$18)/(1+$B19)^ROW(INDIRECT("1:10")))+Assumptions!$C$10*(1-Assumptions!$C$19)/(1+$B19)^10 -> 24350119 | F19: =-Assumptions!$C$12+SUMPRODUCT(((Assumptions!$C$15*(1+F$17)^(ROW(INDIRECT("1:10"))-1)*(1-Assumptions!$C$17)-Assumptions!$C$7/Assumptions!$C$18)*(1-Assumptions!$C$19)+Assumptions!$C$7/Assumptions!$C$18)/(1+$B19)^ROW(INDIRECT("1:10")))+Assumptions!$C$10*(1-Assumptions!$C$19)/(1+$B19)^10 -> 29606202 | G19: =-Assumptions!$C$12+SUMPRODUCT(((Assumptions!$C$15*(1+G$17)^(ROW(INDIRECT("1:10"))-1)*(1-Assumptions!$C$17)-Assumptions!$C$7/Assumptions!$C$18)*(1-Assumptions!$C$19)+Assumptions!$C$7/Assumptions!$C$18)/(1+$B19)^ROW(INDIRECT("1:10")))+Assumptions!$C$10*(1-Assumptions!$C$19)/(1+$B19)^10 -> 35414125 | H19: =-Assumptions!$C$12+SUMPRODUCT(((Assumptions!$C$15*(1+H$17)^(ROW(INDIRECT("1:10"))-1)*(1-Assumptions!$C$17)-Assumptions!$C$7/Assumptions!$C$18)*(1-Assumptions!$C$19)+Assumptions!$C$7/Assumptions!$C$18)/(1+$B19)^ROW(INDIRECT("1:10")))+Assumptions!$C$10*(1-Assumptions!$C$19)/(1+$B19)^10 -> 41831274 | I19: =-Assumptions!$C$12+SUMPRODUCT(((Assumptions!$C$15*(1+I$17)^(ROW(INDIRECT("1:10"))-1)*(1-Assumptions!$C$17)-Assumptions!$C$7/Assumptions!$C$18)*(1-Assumptions!$C$19)+Assumptions!$C$7/Assumptions!$C$18)/(1+$B19)^ROW(INDIRECT("1:10")))+Assumptions!$C$10*(1-Assumptions!$C$19)/(1+$B19)^10 -> 48920454
B20: 0.09 | C20: =-Assumptions!$C$12+SUMPRODUCT(((Assumptions!$C$15*(1+C$17)^(ROW(INDIRECT("1:10"))-1)*(1-Assumptions!$C$17)-Assumptions!$C$7/Assumptions!$C$18)*(1-Assumptions!$C$19)+Assumptions!$C$7/Assumptions!$C$18)/(1+$B20)^ROW(INDIRECT("1:10")))+Assumptions!$C$10*(1-Assumptions!$C$19)/(1+$B20)^10 -> 9901258.1 | D20: =-Assumptions!$C$12+SUMPRODUCT(((Assumptions!$C$15*(1+D$17)^(ROW(INDIRECT("1:10"))-1)*(1-Assumptions!$C$17)-Assumptions!$C$7/Assumptions!$C$18)*(1-Assumptions!$C$19)+Assumptions!$C$7/Assumptions!$C$18)/(1+$B20)^ROW(INDIRECT("1:10")))+Assumptions!$C$10*(1-Assumptions!$C$19)/(1+$B20)^10 -> 13690668 | E20: =-Assumptions!$C$12+SUMPRODUCT(((Assumptions!$C$15*(1+E$17)^(ROW(INDIRECT("1:10"))-1)*(1-Assumptions!$C$17)-Assumptions!$C$7/Assumptions!$C$18)*(1-Assumptions!$C$19)+Assumptions!$C$7/Assumptions!$C$18)/(1+$B20)^ROW(INDIRECT("1:10")))+Assumptions!$C$10*(1-Assumptions!$C$19)/(1+$B20)^10 -> 17869467 | F20: =-Assumptions!$C$12+SUMPRODUCT(((Assumptions!$C$15*(1+F$17)^(ROW(INDIRECT("1:10"))-1)*(1-Assumptions!$C$17)-Assumptions!$C$7/Assumptions!$C$18)*(1-Assumptions!$C$19)+Assumptions!$C$7/Assumptions!$C$18)/(1+$B20)^ROW(INDIRECT("1:10")))+Assumptions!$C$10*(1-Assumptions!$C$19)/(1+$B20)^10 -> 22478324 | G20: =-Assumptions!$C$12+SUMPRODUCT(((Assumptions!$C$15*(1+G$17)^(ROW(INDIRECT("1:10"))-1)*(1-Assumptions!$C$17)-Assumptions!$C$7/Assumptions!$C$18)*(1-Assumptions!$C$19)+Assumptions!$C$7/Assumptions!$C$18)/(1+$B20)^ROW(INDIRECT("1:10")))+Assumptions!$C$10*(1-Assumptions!$C$19)/(1+$B20)^10 -> 27561811 | H20: =-Assumptions!$C$12+SUMPRODUCT(((Assumptions!$C$15*(1+H$17)^(ROW(INDIRECT("1:10"))-1)*(1-Assumptions!$C$17)-Assumptions!$C$7/Assumptions!$C$18)*(1-Assumptions!$C$19)+Assumptions!$C$7/Assumptions!$C$18)/(1+$B20)^ROW(INDIRECT("1:10")))+Assumptions!$C$10*(1-Assumptions!$C$19)/(1+$B20)^10 -> 33168729 | I20: =-Assumptions!$C$12+SUMPRODUCT(((Assumptions!$C$15*(1+I$17)^(ROW(INDIRECT("1:10"))-1)*(1-Assumptions!$C$17)-Assumptions!$C$7/Assumptions!$C$18)*(1-Assumptions!$C$19)+Assumptions!$C$7/Assumptions!$C$18)/(1+$B20)^ROW(INDIRECT("1:10")))+Assumptions!$C$10*(1-Assumptions!$C$19)/(1+$B20)^10 -> 39352455
B21: 0.11 | C21: =-Assumptions!$C$12+SUMPRODUCT(((Assumptions!$C$15*(1+C$17)^(ROW(INDIRECT("1:10"))-1)*(1-Assumptions!$C$17)-Assumptions!$C$7/Assumptions!$C$18)*(1-Assumptions!$C$19)+Assumptions!$C$7/Assumptions!$C$18)/(1+$B21)^ROW(INDIRECT("1:10")))+Assumptions!$C$10*(1-Assumptions!$C$19)/(1+$B21)^10 -> 5211119.7 | D21: =-Assumptions!$C$12+SUMPRODUCT(((Assumptions!$C$15*(1+D$17)^(ROW(INDIRECT("1:10"))-1)*(1-Assumptions!$C$17)-Assumptions!$C$7/Assumptions!$C$18)*(1-Assumptions!$C$19)+Assumptions!$C$7/Assumptions!$C$18)/(1+$B21)^ROW(INDIRECT("1:10")))+Assumptions!$C$10*(1-Assumptions!$C$19)/(1+$B21)^10 -> 8560518.6 | E21: =-Assumptions!$C$12+SUMPRODUCT(((Assumptions!$C$15*(1+E$17)^(ROW(INDIRECT("1:10"))-1)*(1-Assumptions!$C$17)-Assumptions!$C$7/Assumptions!$C$18)*(1-Assumptions!$C$19)+Assumptions!$C$7/Assumptions!$C$18)/(1+$B21)^ROW(INDIRECT("1:10")))+Assumptions!$C$10*(1-Assumptions!$C$19)/(1+$B21)^10 -> 12246862 | F21: =-Assumptions!$C$12+SUMPRODUCT(((Assumptions!$C$15*(1+F$17)^(ROW(INDIRECT("1:10"))-1)*(1-Assumptions!$C$17)-Assumptions!$C$7/Assumptions!$C$18)*(1-Assumptions!$C$19)+Assumptions!$C$7/Assumptions!$C$18)/(1+$B21)^ROW(INDIRECT("1:10")))+Assumptions!$C$10*(1-Assumptions!$C$19)/(1+$B21)^10 -> 16304906 | G21: =-Assumptions!$C$12+SUMPRODUCT(((Assumptions!$C$15*(1+G$17)^(ROW(INDIRECT("1:10"))-1)*(1-Assumptions!$C$17)-Assumptions!$C$7/Assumptions!$C$18)*(1-Assumptions!$C$19)+Assumptions!$C$7/Assumptions!$C$18)/(1+$B21)^ROW(INDIRECT("1:10")))+Assumptions!$C$10*(1-Assumptions!$C$19)/(1+$B21)^10 -> 20772715 | H21: =-Assumptions!$C$12+SUMPRODUCT(((Assumptions!$C$15*(1+H$17)^(ROW(INDIRECT("1:10"))-1)*(1-Assumptions!$C$17)-Assumptions!$C$7/Assumptions!$C$18)*(1-Assumptions!$C$19)+Assumptions!$C$7/Assumptions!$C$18)/(1+$B21)^ROW(INDIRECT("1:10")))+Assumptions!$C$10*(1-Assumptions!$C$19)/(1+$B21)^10 -> 25691939 | I21: =-Assumptions!$C$12+SUMPRODUCT(((Assumptions!$C$15*(1+I$17)^(ROW(INDIRECT("1:10"))-1)*(1-Assumptions!$C$17)-Assumptions!$C$7/Assumptions!$C$18)*(1-Assumptions!$C$19)+Assumptions!$C$7/Assumptions!$C$18)/(1+$B21)^ROW(INDIRECT("1:10")))+Assumptions!$C$10*(1-Assumptions!$C$19)/(1+$B21)^10 -> 31108103
B22: 0.13 | C22: =-Assumptions!$C$12+SUMPRODUCT(((Assumptions!$C$15*(1+C$17)^(ROW(INDIRECT("1:10"))-1)*(1-Assumptions!$C$17)-Assumptions!$C$7/Assumptions!$C$18)*(1-Assumptions!$C$19)+Assumptions!$C$7/Assumptions!$C$18)/(1+$B22)^ROW(INDIRECT("1:10")))+Assumptions!$C$10*(1-Assumptions!$C$19)/(1+$B22)^10 -> 1108175 | D22: =-Assumptions!$C$12+SUMPRODUCT(((Assumptions!$C$15*(1+D$17)^(ROW(INDIRECT("1:10"))-1)*(1-Assumptions!$C$17)-Assumptions!$C$7/Assumptions!$C$18)*(1-Assumptions!$C$19)+Assumptions!$C$7/Assumptions!$C$18)/(1+$B22)^ROW(INDIRECT("1:10")))+Assumptions!$C$10*(1-Assumptions!$C$19)/(1+$B22)^10 -> 4080408.7 | E22: =-Assumptions!$C$12+SUMPRODUCT(((Assumptions!$C$15*(1+E$17)^(ROW(INDIRECT("1:10"))-1)*(1-Assumptions!$C$17)-Assumptions!$C$7/Assumptions!$C$18)*(1-Assumptions!$C$19)+Assumptions!$C$7/Assumptions!$C$18)/(1+$B22)^ROW(INDIRECT("1:10")))+Assumptions!$C$10*(1-Assumptions!$C$19)/(1+$B22)^10 -> 7345274.1 | F22: =-Assumptions!$C$12+SUMPRODUCT(((Assumptions!$C$15*(1+F$17)^(ROW(INDIRECT("1:10"))-1)*(1-Assumptions!$C$17)-Assumptions!$C$7/Assumptions!$C$18)*(1-Assumptions!$C$19)+Assumptions!$C$7/Assumptions!$C$18)/(1+$B22)^ROW(INDIRECT("1:10")))+Assumptions!$C$10*(1-Assumptions!$C$19)/(1+$B22)^10 -> 10932575 | G22: =-Assumptions!$C$12+SUMPRODUCT(((Assumptions!$C$15*(1+G$17)^(ROW(INDIRECT("1:10"))-1)*(1-Assumptions!$C$17)-Assumptions!$C$7/Assumptions!$C$18)*(1-Assumptions!$C$19)+Assumptions!$C$7/Assumptions!$C$18)/(1+$B22)^ROW(INDIRECT("1:10")))+Assumptions!$C$10*(1-Assumptions!$C$19)/(1+$B22)^10 -> 14874934 | H22: =-Assumptions!$C$12+SUMPRODUCT(((Assumptions!$C$15*(1+H$17)^(ROW(INDIRECT("1:10"))-1)*(1-Assumptions!$C$17)-Assumptions!$C$7/Assumptions!$C$18)*(1-Assumptions!$C$19)+Assumptions!$C$7/Assumptions!$C$18)/(1+$B22)^ROW(INDIRECT("1:10")))+Assumptions!$C$10*(1-Assumptions!$C$19)/(1+$B22)^10 -> 19208017 | I22: =-Assumptions!$C$12+SUMPRODUCT(((Assumptions!$C$15*(1+I$17)^(ROW(INDIRECT("1:10"))-1)*(1-Assumptions!$C$17)-Assumptions!$C$7/Assumptions!$C$18)*(1-Assumptions!$C$19)+Assumptions!$C$7/Assumptions!$C$18)/(1+$B22)^ROW(INDIRECT("1:10")))+Assumptions!$C$10*(1-Assumptions!$C$19)/(1+$B22)^10 -> 23970787
B23: 0.15 | C23: =-Assumptions!$C$12+SUMPRODUCT(((Assumptions!$C$15*(1+C$17)^(ROW(INDIRECT("1:10"))-1)*(1-Assumptions!$C$17)-Assumptions!$C$7/Assumptions!$C$18)*(1-Assumptions!$C$19)+Assumptions!$C$7/Assumptions!$C$18)/(1+$B23)^ROW(INDIRECT("1:10")))+Assumptions!$C$10*(1-Assumptions!$C$19)/(1+$B23)^10 -> -2497809.6 | D23: =-Assumptions!$C$12+SUMPRODUCT(((Assumptions!$C$15*(1+D$17)^(ROW(INDIRECT("1:10"))-1)*(1-Assumptions!$C$17)-Assumptions!$C$7/Assumptions!$C$18)*(1-Assumptions!$C$19)+Assumptions!$C$7/Assumptions!$C$18)/(1+$B23)^ROW(INDIRECT("1:10")))+Assumptions!$C$10*(1-Assumptions!$C$19)/(1+$B23)^10 -> 149801.69 | E23: =-Assumptions!$C$12+SUMPRODUCT(((Assumptions!$C$15*(1+E$17)^(ROW(INDIRECT("1:10"))-1)*(1-Assumptions!$C$17)-Assumptions!$C$7/Assumptions!$C$18)*(1-Assumptions!$C$19)+Assumptions!$C$7/Assumptions!$C$18)/(1+$B23)^ROW(INDIRECT("1:10")))+Assumptions!$C$10*(1-Assumptions!$C$19)/(1+$B23)^10 -> 3052458.1 | F23: =-Assumptions!$C$12+SUMPRODUCT(((Assumptions!$C$15*(1+F$17)^(ROW(INDIRECT("1:10"))-1)*(1-Assumptions!$C$17)-Assumptions!$C$7/Assumptions!$C$18)*(1-Assumptions!$C$19)+Assumptions!$C$7/Assumptions!$C$18)/(1+$B23)^ROW(INDIRECT("1:10")))+Assumptions!$C$10*(1-Assumptions!$C$19)/(1+$B23)^10 -> 6235804.4 | G23: =-Assumptions!$C$12+SUMPRODUCT(((Assumptions!$C$15*(1+G$17)^(ROW(INDIRECT("1:10"))-1)*(1-Assumptions!$C$17)-Assumptions!$C$7/Assumptions!$C$18)*(1-Assumptions!$C$19)+Assumptions!$C$7/Assumptions!$C$18)/(1+$B23)^ROW(INDIRECT("1:10")))+Assumptions!$C$10*(1-Assumptions!$C$19)/(1+$B23)^10 -> 9727888.4 | H23: =-Assumptions!$C$12+SUMPRODUCT(((Assumptions!$C$15*(1+H$17)^(ROW(INDIRECT("1:10"))-1)*(1-Assumptions!$C$17)-Assumptions!$C$7/Assumptions!$C$18)*(1-Assumptions!$C$19)+Assumptions!$C$7/Assumptions!$C$18)/(1+$B23)^ROW(INDIRECT("1:10")))+Assumptions!$C$10*(1-Assumptions!$C$19)/(1+$B23)^10 -> 13559358 | I23: =-Assumptions!$C$12+SUMPRODUCT(((Assumptions!$C$15*(1+I$17)^(ROW(INDIRECT("1:10"))-1)*(1-Assumptions!$C$17)-Assumptions!$C$7/Assumptions!$C$18)*(1-Assumptions!$C$19)+Assumptions!$C$7/Assumptions!$C$18)/(1+$B23)^ROW(INDIRECT("1:10")))+Assumptions!$C$10*(1-Assumptions!$C$19)/(1+$B23)^10 -> 17763668
B25: Double-bordered cell = base-case assumptions (9% WACC, 6% revenue growth).

Sheet Customer LTV
B2: CUSTOMER LIFETIME VALUE (CLV) MODEL
B3: CLV = Annual Contribution per Customer x Average Customer Lifespan, less Acquisition Cost. Sanity-checks the commercial case for the route.
B5: Driver | C5: Value
B6: Average fare per ticket | C6: =Assumptions!C23 -> 850
B7: Average trips per customer per year | C7: =Assumptions!C24 -> 2.4
B8: Annual customer retention rate | C8: =Assumptions!C25 -> 0.72
B9: Contribution margin per ticket | C9: =Assumptions!C26 -> 0.34
B10: Customer acquisition cost (CAC) | C10: =Assumptions!C27 -> 140
B12: CLV CALCULATION
B13: Annual Revenue per Customer | C13: =C6*C7 -> 2040
B14: Annual Contribution per Customer | C14: =C13*C9 -> 693.6
B15: Average Customer Lifespan (Years) = 1 / (1 - retention) | C15: =1/(1-C8) -> 3.5714286
B16: Gross Customer Lifetime Value (undiscounted) | C16: =C14*C15 -> 2477.1429
B17: Less: Customer Acquisition Cost | C17: =-C10 -> -140
B18: NET CUSTOMER LIFETIME VALUE (CLV) | C18: =C16-C10 -> 2337.1429
B19: CLV : CAC Ratio (should exceed 3.0x for a healthy program) | C19: =C16/C10 -> 17.693878
B21: DISCOUNTED CLV (TIME VALUE OF MONEY)
B22: Applies WACC to discount each future year of the average customer lifespan back to present value.
B23: Year | C23: Retained Customer % | D23: Contribution | E23: Discount Factor | F23: PV of Contribution
B24: Year 1 | C24: =1 -> 1 | D24: =C24*$C$14 -> 693.6 | E24: =1/(1+Assumptions!$C$20)^1 -> 0.91743119 | F24: =D24*E24 -> 636.33028
B25: Year 2 | C25: =C24*$C$8 -> 0.72 | D25: =C25*$C$14 -> 499.392 | E25: =1/(1+Assumptions!$C$20)^2 -> 0.84167999 | F25: =D25*E25 -> 420.32826
B26: Year 3 | C26: =C25*$C$8 -> 0.5184 | D26: =C26*$C$14 -> 359.56224 | E26: =1/(1+Assumptions!$C$20)^3 -> 0.77218348 | F26: =D26*E26 -> 277.64802
B27: Year 4 | C27: =C26*$C$8 -> 0.373248 | D27: =C27*$C$14 -> 258.88481 | E27: =1/(1+Assumptions!$C$20)^4 -> 0.70842521 | F27: =D27*E27 -> 183.40053
B28: Year 5 | C28: =C27*$C$8 -> 0.26873856 | D28: =C28*$C$14 -> 186.39707 | E28: =1/(1+Assumptions!$C$20)^5 -> 0.64993139 | F28: =D28*E28 -> 121.1453
B29: Year 6 | C29: =C28*$C$8 -> 0.19349176 | D29: =C29*$C$14 -> 134.20589 | E29: =1/(1+Assumptions!$C$20)^6 -> 0.59626733 | F29: =D29*E29 -> 80.022585
B30: Year 7 | C30: =C29*$C$8 -> 0.13931407 | D30: =C30*$C$14 -> 96.628239 | E30: =1/(1+Assumptions!$C$20)^7 -> 0.54703424 | F30: =D30*E30 -> 52.858956
B31: Year 8 | C31: =C30*$C$8 -> 0.10030613 | D31: =C31*$C$14 -> 69.572332 | E31: =1/(1+Assumptions!$C$20)^8 -> 0.50186628 | F31: =D31*E31 -> 34.916007
B32: Year 9 | C32: =C31*$C$8 -> 0.072220414 | D32: =C32*$C$14 -> 50.092079 | E32: =1/(1+Assumptions!$C$20)^9 -> 0.46042778 | F32: =D32*E32 -> 23.063785
B33: Year 10 | C33: =C32*$C$8 -> 0.051998698 | D33: =C33*$C$14 -> 36.066297 | E33: =1/(1+Assumptions!$C$20)^10 -> 0.42241081 | F33: =D33*E33 -> 15.234794
B35: Discounted CLV (10-yr horizon, before CAC) | C35: =SUM(F24:F33) -> 1844.9485
B36: Discounted Net CLV (after CAC) | C36: =C35-C10 -> 1704.9485
B38: INTERPRETATION
B39: A CLV:CAC ratio above 3.0x signals the route's loyalty economics are healthy enough to justify the marketing spend required to fill premium cabins. This complements the NPV/IRR view by testing the demand side, not just the capex side, of the investment case.

Sheet Break-Even Analysis
B2: BREAK-EVEN ANALYSIS
B3: Solves for the passenger volume / load factor at which the route exactly covers fixed and variable costs.
B5: Driver | C5: Value
B6: Annual fixed costs | C6: =Assumptions!C30 -> 21000000
B7: Variable cost per passenger | C7: =Assumptions!C31 -> 310
B8: Average ticket price per passenger | C8: =Assumptions!C32 -> 850
B9: Aircraft seat capacity | C9: =Assumptions!C33 -> 296
B10: Planned annual frequencies (round trips) | C10: =Assumptions!C34 -> 365
B12: BREAK-EVEN CALCULATION
B13: Contribution Margin per Passenger | C13: =C8-C7 -> 540
B14: Contribution Margin % | C14: =C13/C8 -> 0.63529412
B15: BREAK-EVEN PASSENGERS PER YEAR | C15: =C6/C13 -> 38888.889
B16: BREAK-EVEN REVENUE PER YEAR | C16: =C15*C8 -> 33055556
B17: Total Annual Seat Capacity (seats x round trips x 2 legs) | C17: =C9*C10*2 -> 216080
B18: BREAK-EVEN LOAD FACTOR (% of seats that must be filled) | C18: =C15/C17 -> 0.1799745
B19: Expected Annual Passengers (using Year 1 revenue assumption) | C19: =Assumptions!C15/C8 -> 37647.059
B20: Expected Load Factor | C20: =C19/C17 -> 0.17422741
B21: Margin of Safety (Expected Load Factor less Break-Even Load Factor) | C21: =C20-C18 -> -0.0057470847
B23: LOAD FACTOR SENSITIVITY - ANNUAL PROFIT / (LOSS)
B25: Load Factor | C25: Annual Profit / (Loss)
B26: 0.5 | C26: =B26*$C$17*$C$13-$C$6 -> 37341600
B27: 0.55 | C27: =B27*$C$17*$C$13-$C$6 -> 43175760
B28: 0.6 | C28: =B28*$C$17*$C$13-$C$6 -> 49009920
B29: 0.65 | C29: =B29*$C$17*$C$13-$C$6 -> 54844080
B30: 0.7 | C30: =B30*$C$17*$C$13-$C$6 -> 60678240
B31: 0.75 | C31: =B31*$C$17*$C$13-$C$6 -> 66512400
B32: 0.8 | C32: =B32*$C$17*$C$13-$C$6 -> 72346560
B33: 0.85 | C33: =B33*$C$17*$C$13-$C$6 -> 78180720
B34: 0.9 | C34: =B34*$C$17*$C$13-$C$6 -> 84014880
B35: 0.95 | C35: =B35*$C$17*$C$13-$C$6 -> 89849040
B37: INTERPRETATION
B38: The route must fill roughly the break-even load factor of every flight to cover fixed and variable costs. Comparing this to the expected load factor from the commercial forecast shows the operating margin of safety before the route turns unprofitable.
